agent/__init__.py
agent/main.py
scratchagent-0.1.0.dist-info/licenses/LICENSE
scratchagent-0.1.0.dist-info/METADATA
scratchagent-0.1.0.dist-info/WHEEL
scratchagent-0.1.0.dist-info/entry_points.txt
scratchagent-0.1.0.dist-info/top_level.txt
scratchagent-0.1.0.dist-info/RECORD
