Metadata-Version: 2.4
Name: ScratchAgent
Version: 0.1.0
Summary: A Python agent framework for building intelligent automation tools
Author-email: Qaadir <qaadireng@gmail.com>
License: MIT
Project-URL: Homepage, https://github.com/AbQaadir/ScratchAgent
Project-URL: Bug Tracker, https://github.com/AbQaadir/ScratchAgent/issues
Project-URL: Repository, https://github.com/AbQaadir/ScratchAgent
Keywords: agent,automation,ai,framework
Classifier: Development Status :: 3 - Alpha
Classifier: Intended Audience :: Developers
Classifier: License :: OSI Approved :: MIT License
Classifier: Programming Language :: Python :: 3
Classifier: Programming Language :: Python :: 3.9
Classifier: Programming Language :: Python :: 3.10
Classifier: Programming Language :: Python :: 3.11
Classifier: Programming Language :: Python :: 3.12
Classifier: Programming Language :: Python :: 3.13
Classifier: Topic :: Software Development :: Libraries :: Python Modules
Requires-Python: >=3.9
License-File: LICENSE
Requires-Dist: pytest>=8.4.2
Requires-Dist: requests>=2.20.0
Provides-Extra: dev
Requires-Dist: build>=1.0.0; extra == "dev"
Requires-Dist: twine>=4.0.0; extra == "dev"
Requires-Dist: pytest>=7.0.0; extra == "dev"
Requires-Dist: pytest-cov>=4.0.0; extra == "dev"
Dynamic: license-file
